{
  "myreviews": [],
  "cart": [],
  "myfavoriteCourses": {
    "courses": []
  },
  "mybought": {
    "courses": []
  },
  "courses": [
    {
      "id": "c001",
      "courseName": "Front-end",
      "coursePrice": 500,
      "courseImage": "assets/images/logo.png",
      "courseRating": 4.3,
      "countRating": 3,
      "courseAddedDate": "2024-09-30",
      "category": [
        "Front-end",
        "Web Development",
        "KongRuksiam"
      ],
      "tutorName": "KongRuksiam",
      "isFavorite": false,
      "bought": false
    },
    {
      "id": "c002",
      "courseName": "Back-end",
      "coursePrice": 500,
      "courseImage": "assets/images/logo.png",
      "courseRating": 4.5,
      "countRating": 3,
      "courseAddedDate": "2024-06-30",
      "category": [
        "Back-end",
        "Web Development",
        "BorntoDev"
      ],
      "tutorName": "BorntoDev",
      "isFavorite": false,
      "bought": false
    },
    {
      "id": "c003",
      "courseName": "PowerBI",
      "coursePrice": 300,
      "courseImage": "assets/images/logo.png",
      "courseRating": 3.8,
      "countRating": 3,
      "courseAddedDate": "2024-07-30",
      "category": [
        "Data Analytics",
        "Zinglecode"
      ],
      "tutorName": "Zinglecode",
      "isFavorite": false,
      "bought": false
    },
    {
      "id": "c004",
      "courseName": "Analytic Tools",
      "coursePrice": 300,
      "courseImage": "assets/images/logo.png",
      "courseRating": 4,
      "countRating": 3,
      "courseAddedDate": "2024-01-30",
      "category": [
        "Data Analytics",
        "KongRuksiam"
      ],
      "tutorName": "KongRuksiam",
      "isFavorite": false,
      "bought": false
    }
  ]
}